LICENSE.md
MANIFEST.in
README.md
setup.cfg
setup.py
libpurecool/__init__.py
libpurecool/const.py
libpurecool/dyson.py
libpurecool/dyson_360_eye.py
libpurecool/dyson_device.py
libpurecool/dyson_pure_cool.py
libpurecool/dyson_pure_cool_link.py
libpurecool/dyson_pure_hotcool.py
libpurecool/dyson_pure_hotcool_link.py
libpurecool/dyson_pure_state.py
libpurecool/dyson_pure_state_v2.py
libpurecool/exceptions.py
libpurecool/utils.py
libpurecool/zeroconf.py
libpurecool.egg-info/PKG-INFO
libpurecool.egg-info/SOURCES.txt
libpurecool.egg-info/dependency_links.txt
libpurecool.egg-info/requires.txt
libpurecool.egg-info/top_level.txt
libpurecool.egg-info/zip-safe